<odoo>
    <data>
        <template id="listing" name="Landing Module">
            <xpath expr="." position="inside">
                <!-- <base href="./" /> -->
                <meta name="viewport" content="width=device-width, initial-scale=1.0" />
            </xpath>
        </template>
        
        <!-- <template id="assets_frontend" inherit_id="website.assets_frontend" name="Landing Module">
            <xpath expr="." position="inside">
                
                <link rel="stylesheet" type="text/css" href="/angular_website/static/src/css/main.css" />
            </xpath>
        </template> -->
        
        <template id="index" name="Landing Page">
                <div id="app"></div>
                <script type="text/javascript" src="/angular_website/static/src/js/app.js"></script>
                <!-- Hotjar Tracking Code for www.3mit.dev -->
                <script>
                    (function(h,o,t,j,a,r){
                        h.hj=h.hj||function(){(h.hj.q=h.hj.q||[]).push(arguments)};
                        h._hjSettings={hjid:1669321,hjsv:6};
                        a=o.getElementsByTagName('head')[0];
                        r=o.createElement('script');r.async=1;
                        r.src=t+h._hjSettings.hjid+j+h._hjSettings.hjsv;
                        a.appendChild(r);
                    })(window,document,'https://static.hotjar.com/c/hotjar-','.js?sv=');
                </script>
<!--             <app-root></app-root> -->
<!--             <script type="text/javascript" src="/angular_website/static/src/js/main-es5.js"></script>
            <script type="text/javascript" src="/angular_website/static/src/js/main-es2015.js"></script>
            <script type="text/javascript" src="/angular_website/static/src/js/polyfills-es5.js"></script>
            <script type="text/javascript" src="/angular_website/static/src/js/polyfills-es2015.js"></script>
            <script type="text/javascript" src="/angular_website/static/src/js/runtime-es5.js"></script>
            <script type="text/javascript" src="/angular_website/static/src/js/runtime-es2015.js"></script> -->
        </template>
    </data>
</odoo>